azure_blob_utils/__init__.py
azure_blob_utils/file_utils.py
azure_blob_utils/storage_helper.py
azure_blob_utils_croston-0.3.0.dist-info/METADATA
azure_blob_utils_croston-0.3.0.dist-info/WHEEL
azure_blob_utils_croston-0.3.0.dist-info/top_level.txt
azure_blob_utils_croston-0.3.0.dist-info/RECORD
