Metadata-Version: 2.4
Name: azure-blob-utils-croston
Version: 0.3.0
Summary: Utility functions for Azure Blob Storage access
Author-email: Jeff Croston <crostonj@gmail.com>
License: MIT
Project-URL: Homepage, https://github.com/crostonj/pystorage
Project-URL: Repository, https://github.com/crostonj/pystorage
Requires-Python: >=3.8
Requires-Dist: azure-storage-blob>=12.0.0
